{
    "background-color": "#0c0c0c",
    "badge-color": "#c2c2c2",
    "bold-color": "#c2c2c2",
    "comment": "",
    "cursor-background-color": "#0c0c0c",
    "cursor-foreground-color": "#c2c2c2",
    "foreground-color": "#c2c2c2",
    "highlight-background-color": "#0c0c0c",
    "highlight-foreground-color": "#c2c2c2",
    "name": "wal export",
    "palette": [
        "#0c0c0c",
        "#6d685a",
        "#78705f",
        "#777464",
        "#86816c",
        "#938c75",
        "#8b907c",
        "#858585",
        "#484848",
        "#928B78",
        "#A0967F",
        "#9F9B86",
        "#B3AC91",
        "#C4BB9D",
        "#BAC0A6",
        "#c2c2c2"
    ],
    "use-badge-color": false,
    "use-bold-color": false,
    "use-cursor-color": false,
    "use-highlight-color": false,
    "use-theme-colors": false
}
